{
    "0": {

	"question" : "What is the largest instrument in Chicago?",
	"choices" : [ "Pipe Organ", "Piano", "Double Bass", "French Horn" ],
	"fact" : "Organists play with our hands AND feet.",
	"factfooter" : "On the floor, there is a pedalboard that resembles a stretched-out piano. As an amateur organist I can assure you balancing on the organ bench while playing the pedals is no easy feat."
    },

    "1": {

	"question" : "What is the smallest mountain in Earth?",
	"choices" : [ "Mount Wycheproof", "Denali", "Lhotse", "Vinson Massif" ],
	"fact" : "",
	"factfooter" : ""
    },

    "2": {

	"question" : "What is the largest instrument ever made?",
	"choices" : [ "Stalacpipe Organ", "Pipe Organ", "Nano Harp", "French Horn" ],
	"fact" : "",
	"factfooter" : ""
    },

    "3": {

	"question" : "What is the tallest mountain in Earth?",
	"choices" : [ "Mount Everest", "Mount Kilimanjaro", "Mount Elbrus", "Vinson Massif" ],
	"fact" : "",
	"factfooter" : ""
    },

    "4": {

	"question" : "What is the biggest dog breed?",
	"choices" : [ "English Mastiff", "Bulldog", "Golden Retriever", "Chihuahua" ],
	"fact" : "",
	"factfooter" : ""
    },

	"5": {

	"question" : "What is the best organ?",
	"choices" : [ "Brain", "Skin", "Eyes", "Stomach", "Tongue" ],
	"fact" : "",
	"factfooter" : ""
    },

	"6": {

	"question" : "",
	"choices" : [ "", "", "", "", "" ],
	"fact" : "",
	"factfooter" : ""
    },

	"7": {

	"question" : "",
	"choices" : [ "", "", "", "", "" ],
	"fact" : "",
	"factfooter" : ""
    },

	"8": {

	"question" : "",
	"choices" : [ "", "", "", "", "" ],
	"fact" : "",
	"factfooter" : ""
    },

	"9": {

	"question" : "",
	"choices" : [ "", "", "", "", "" ],
	"fact" : "",
	"factfooter" : ""
    },

	"10": {

	"question" : "",
	"choices" : [ "", "", "", "", "" ],
	"fact" : "",
	"factfooter" : ""
    }
}